{
    "openapi": "3.0.0",
    "info": {
        "title": "API Finance - Gestion des Comptes",
        "description": "API RESTful pour la gestion des comptes bancaires",
        "version": "1.0.0"
    },
    "servers": [
        {
            "url": "http://localhost:8000/api",
            "description": "Serveur de développement"
        }
    ],
    "paths": {
        "/v1/comptes": {
            "get": {
                "tags": [
                    "Comptes"
                ],
                "summary": "Lister tous les comptes",
                "description": "Récupère la liste paginée des comptes avec possibilité de filtrage et tri",
                "operationId": "getComptes",
                "parameters": [
                    {
                        "name": "page",
                        "in": "query",
                        "description": "Numéro de page",
                        "required": false,
                        "schema": {
                            "type": "integer",
                            "default": 1,
                            "minimum": 1
                        }
                    },
                    {
                        "name": "limit",
                        "in": "query",
                        "description": "Nombre d'éléments par page",
                        "required": false,
                        "schema": {
                            "type": "integer",
                            "default": 10,
                            "maximum": 100,
                            "minimum": 1
                        }
                    },
                    {
                        "name": "type",
                        "in": "query",
                        "description": "Type de compte",
                        "required": false,
                        "schema": {
                            "type": "string",
                            "enum": [
                                "cheque",
                                "courant",
                                "epargne"
                            ]
                        }
                    },
                    {
                        "name": "statut",
                        "in": "query",
                        "description": "Statut du compte",
                        "required": false,
                        "schema": {
                            "type": "string",
                            "enum": [
                                "actif",
                                "inactif",
                                "bloque",
                                "ferme"
                            ]
                        }
                    },
                    {
                        "name": "search",
                        "in": "query",
                        "description": "Recherche par titulaire ou numéro",
                        "required": false,
                        "schema": {
                            "type": "string"
                        }
                    },
                    {
                        "name": "sort",
                        "in": "query",
                        "description": "Champ de tri",
                        "required": false,
                        "schema": {
                            "type": "string",
                            "default": "dateCreation",
                            "enum": [
                                "dateCreation",
                                "solde",
                                "titulaire",
                                "numeroCompte"
                            ]
                        }
                    },
                    {
                        "name": "order",
                        "in": "query",
                        "description": "Ordre de tri",
                        "required": false,
                        "schema": {
                            "type": "string",
                            "default": "desc",
                            "enum": [
                                "asc",
                                "desc"
                            ]
                        }
                    }
                ],
                "responses": {
                    "200": {
                        "description": "Liste des comptes récupérée avec succès",
                        "content": {
                            "application/json": {
                                "schema": {
                                    "properties": {
                                        "success": {
                                            "type": "boolean",
                                            "example": true
                                        },
                                        "data": {
                                            "type": "array",
                                            "items": {
                                                "properties": {
                                                    "id": {
                                                        "type": "string",
                                                        "format": "uuid",
                                                        "example": "550e8400-e29b-41d4-a716-446655440000"
                                                    },
                                                    "numeroCompte": {
                                                        "type": "string",
                                                        "example": "C00123456"
                                                    },
                                                    "titulaire": {
                                                        "type": "string",
                                                        "example": "Amadou Diallo"
                                                    },
                                                    "type": {
                                                        "type": "string",
                                                        "enum": [
                                                            "cheque",
                                                            "courant",
                                                            "epargne"
                                                        ],
                                                        "example": "epargne"
                                                    },
                                                    "solde": {
                                                        "type": "number",
                                                        "format": "float",
                                                        "example": 1250000
                                                    },
                                                    "devise": {
                                                        "type": "string",
                                                        "example": "XAF"
                                                    },
                                                    "dateCreation": {
                                                        "type": "string",
                                                        "format": "date-time",
                                                        "example": "2023-03-15T00:00:00Z"
                                                    },
                                                    "statut": {
                                                        "type": "string",
                                                        "enum": [
                                                            "actif",
                                                            "inactif",
                                                            "bloque",
                                                            "ferme"
                                                        ],
                                                        "example": "bloque"
                                                    },
                                                    "motifBlocage": {
                                                        "type": "string",
                                                        "example": "Inactivité de 30+ jours",
                                                        "nullable": true
                                                    },
                                                    "metadata": {
                                                        "properties": {
                                                            "derniereModification": {
                                                                "type": "string",
                                                                "format": "date-time",
                                                                "example": "2023-06-10T14:30:00Z"
                                                            },
                                                            "version": {
                                                                "type": "integer",
                                                                "example": 1
                                                            }
                                                        },
                                                        "type": "object"
                                                    }
                                                },
                                                "type": "object"
                                            }
                                        },
                                        "pagination": {
                                            "properties": {
                                                "currentPage": {
                                                    "type": "integer",
                                                    "example": 1
                                                },
                                                "totalPages": {
                                                    "type": "integer",
                                                    "example": 3
                                                },
                                                "totalItems": {
                                                    "type": "integer",
                                                    "example": 25
                                                },
                                                "itemsPerPage": {
                                                    "type": "integer",
                                                    "example": 10
                                                },
                                                "hasNext": {
                                                    "type": "boolean",
                                                    "example": true
                                                },
                                                "hasPrevious": {
                                                    "type": "boolean",
                                                    "example": false
                                                }
                                            },
                                            "type": "object"
                                        },
                                        "links": {
                                            "properties": {
                                                "self": {
                                                    "type": "string",
                                                    "example": "/api/v1/comptes?page=1&limit=10"
                                                },
                                                "first": {
                                                    "type": "string",
                                                    "example": "/api/v1/comptes?page=1"
                                                },
                                                "last": {
                                                    "type": "string",
                                                    "example": "/api/v1/comptes?page=3"
                                                },
                                                "next": {
                                                    "type": "string",
                                                    "example": "/api/v1/comptes?page=2",
                                                    "nullable": true
                                                },
                                                "previous": {
                                                    "type": "string",
                                                    "example": "/api/v1/comptes?page=1",
                                                    "nullable": true
                                                }
                                            },
                                            "type": "object"
                                        }
                                    },
                                    "type": "object"
                                }
                            }
                        }
                    },
                    "400": {
                        "description": "Paramètres invalides",
                        "content": {
                            "application/json": {
                                "schema": {
                                    "properties": {
                                        "message": {
                                            "type": "string",
                                            "example": "Validation failed"
                                        },
                                        "errors": {
                                            "type": "object"
                                        }
                                    },
                                    "type": "object"
                                }
                            }
                        }
                    }
                }
            }
        },
        "/v1/comptes/{compteId}": {
            "get": {
                "tags": [
                    "Comptes"
                ],
                "summary": "Récupérer un compte spécifique",
                "description": "Récupère les détails d'un compte spécifique. Admin peut voir tous les comptes, Client seulement les siens.",
                "operationId": "getCompte",
                "parameters": [
                    {
                        "name": "compteId",
                        "in": "path",
                        "description": "ID du compte à récupérer",
                        "required": true,
                        "schema": {
                            "type": "string",
                            "format": "uuid"
                        }
                    }
                ],
                "responses": {
                    "200": {
                        "description": "Détails du compte récupérés avec succès",
                        "content": {
                            "application/json": {
                                "schema": {
                                    "properties": {
                                        "success": {
                                            "type": "boolean",
                                            "example": true
                                        },
                                        "data": {
                                            "properties": {
                                                "id": {
                                                    "type": "string",
                                                    "format": "uuid",
                                                    "example": "550e8400-e29b-41d4-a716-446655440000"
                                                },
                                                "numeroCompte": {
                                                    "type": "string",
                                                    "example": "C00123456"
                                                },
                                                "titulaire": {
                                                    "type": "string",
                                                    "example": "Amadou Diallo"
                                                },
                                                "type": {
                                                    "type": "string",
                                                    "enum": [
                                                        "cheque",
                                                        "courant",
                                                        "epargne"
                                                    ],
                                                    "example": "epargne"
                                                },
                                                "solde": {
                                                    "type": "number",
                                                    "format": "float",
                                                    "example": 1250000
                                                },
                                                "devise": {
                                                    "type": "string",
                                                    "example": "XAF"
                                                },
                                                "dateCreation": {
                                                    "type": "string",
                                                    "format": "date-time",
                                                    "example": "2023-03-15T00:00:00Z"
                                                },
                                                "statut": {
                                                    "type": "string",
                                                    "enum": [
                                                        "actif",
                                                        "inactif",
                                                        "bloque",
                                                        "ferme"
                                                    ],
                                                    "example": "bloque"
                                                },
                                                "motifBlocage": {
                                                    "type": "string",
                                                    "example": "Inactivité de 30+ jours",
                                                    "nullable": true
                                                },
                                                "metadata": {
                                                    "properties": {
                                                        "derniereModification": {
                                                            "type": "string",
                                                            "format": "date-time",
                                                            "example": "2023-06-10T14:30:00Z"
                                                        },
                                                        "version": {
                                                            "type": "integer",
                                                            "example": 1
                                                        }
                                                    },
                                                    "type": "object"
                                                }
                                            },
                                            "type": "object"
                                        }
                                    },
                                    "type": "object"
                                }
                            }
                        }
                    },
                    "404": {
                        "description": "Compte non trouvé",
                        "content": {
                            "application/json": {
                                "schema": {
                                    "properties": {
                                        "success": {
                                            "type": "boolean",
                                            "example": false
                                        },
                                        "error": {
                                            "properties": {
                                                "code": {
                                                    "type": "string",
                                                    "example": "COMPTE_NOT_FOUND"
                                                },
                                                "message": {
                                                    "type": "string",
                                                    "example": "Le compte avec l'ID spécifié n'existe pas"
                                                },
                                                "details": {
                                                    "properties": {
                                                        "compteId": {
                                                            "type": "string",
                                                            "format": "uuid",
                                                            "example": "550e8400-e29b-41d4-a716-446655440000"
                                                        }
                                                    },
                                                    "type": "object"
                                                }
                                            },
                                            "type": "object"
                                        }
                                    },
                                    "type": "object"
                                }
                            }
                        }
                    },
                    "400": {
                        "description": "ID invalide",
                        "content": {
                            "application/json": {
                                "schema": {
                                    "properties": {
                                        "success": {
                                            "type": "boolean",
                                            "example": false
                                        },
                                        "error": {
                                            "properties": {
                                                "code": {
                                                    "type": "string",
                                                    "example": "INVALID_UUID"
                                                },
                                                "message": {
                                                    "type": "string",
                                                    "example": "L'ID du compte doit être un UUID valide"
                                                },
                                                "details": {
                                                    "properties": {
                                                        "compteId": {
                                                            "type": "string",
                                                            "example": "invalid-id"
                                                        }
                                                    },
                                                    "type": "object"
                                                }
                                            },
                                            "type": "object"
                                        }
                                    },
                                    "type": "object"
                                }
                            }
                        }
                    },
                    "403": {
                        "description": "Accès non autorisé",
                        "content": {
                            "application/json": {
                                "schema": {
                                    "properties": {
                                        "success": {
                                            "type": "boolean",
                                            "example": false
                                        },
                                        "error": {
                                            "properties": {
                                                "code": {
                                                    "type": "string",
                                                    "example": "ACCESS_DENIED"
                                                },
                                                "message": {
                                                    "type": "string",
                                                    "example": "Vous n'avez pas accès à ce compte"
                                                }
                                            },
                                            "type": "object"
                                        }
                                    },
                                    "type": "object"
                                }
                            }
                        }
                    }
                }
            }
        }
    },
    "tags": [
        {
            "name": "Comptes",
            "description": "Comptes"
        }
    ]
}